djangoldp_dhde/__init__.py
djangoldp_dhde/apps.py
djangoldp_dhde/models.py
djangoldp_dhde/migrations/__init__.py
djangoldp_dhde/templates/base.html
djangoldp_dhde/templates/email.html
djangoldp_dhde/templates/admin/login.html
djangoldp_dhde/templates/oidc_provider/authorize.html
djangoldp_dhde/templates/password/email.html
djangoldp_dhde/templates/registration/login.html
djangoldp_dhde/templates/registration/password_change_done.html
djangoldp_dhde/templates/registration/password_reset_complete.html
djangoldp_dhde/templates/registration/password_reset_confirm.html
djangoldp_dhde/templates/registration/password_reset_done.html
djangoldp_dhde/templates/registration/password_reset_email.html
djangoldp_dhde/templates/registration/password_reset_form.html
djangoldp_dhde-1.0.0.dist-info/METADATA
djangoldp_dhde-1.0.0.dist-info/WHEEL
djangoldp_dhde-1.0.0.dist-info/top_level.txt
djangoldp_dhde-1.0.0.dist-info/RECORD
