Metadata-Version: 2.1
Name: djangoldp-dhde
Version: 1.0.0
Summary: djangoldp package for Spacecoop-DHDE
Home-page: https://git.startinblox.com/djangoldp-packages/djangoldp-dhde
Author: Startin'blox
Author-email: benoit@startinblox.com
License: MIT
Platform: UNKNOWN
Requires-Dist: djangoldp (~=5.0.0)
Provides-Extra: include_package_data
Requires-Dist: True ; extra == 'include_package_data'
